{"transformName": "ASHE Pensions: Tables 6 & 10", "inputs": {"1": {"distinctiveText": "6.1a", "format": "xls", "name": "ASHE Pensions 6 data"}, "3": {"distinctiveText": "10.1a", "format": "xls", "name": "ASHE Pensions 10 data"}, "2": {"format": "xls", "name": "ASHE Pensions 6 CV", "distinctiveTexat": "6.1b"}, "4": {"format": "xls", "name": "ASHE Pensions 10 CV", "distinctiveTexat": "10.1b"}}, "description": "Takes 4 files: Values for tables 6 and 10, and CVs for tables 6 and 10. Generates a 1 percentage and 1 values output. Both outputs require all 4 inputs.", "outputs": ["ASHE Pensions Tables 6 and 10 Values <year>.csv", "ASHE Pensions Tables 6 and 10 Percentages <year>.csv"], "uses": ["databaker", "pandas"], "transformType": "many-to-many"}